[
  {
    "id": "c8bfc55b-acde-4145-83db-d30db52ea6f5",
    "name": "joaozinho",
    "count": 35,
    "lastUpdated": "2025-05-23T19:59:47.500Z"
  },
  {
    "id": "4a005568-3a28-4a84-ba3b-4a0741172876",
    "name": "Nathan",
    "count": 31,
    "lastUpdated": "2025-05-23T20:02:54.711Z"
  },
  {
    "id": "327e9991-d8f4-46c8-9c58-6a73c070e261",
    "name": "16",
    "count": 26,
    "lastUpdated": "2025-05-23T20:05:47.387Z"
  },
  {
    "id": "bf6614cb-d5c6-4a66-91f6-b413484cd231",
    "name": "Celinho",
    "count": 31,
    "lastUpdated": "2025-05-23T19:40:44.569Z"
  },
  {
    "id": "a102f4c9-f0d8-40df-8510-6049af9feeb4",
    "name": "Eduardo",
    "count": 36,
    "lastUpdated": "2025-05-23T19:42:04.321Z"
  }
]